crispy/BGExp.py
crispy/Bedit.py
crispy/CRISPRData.py
crispy/CopyNumberCorrection.py
crispy/CrispyPlot.py
crispy/DataImporter.py
crispy/DimensionReduction.py
crispy/Enrichment.py
crispy/GIPlot.py
crispy/GuideDesign.py
crispy/GuideSelection.py
crispy/LMModels.py
crispy/LibRepresentationReport.py
crispy/MOFA.py
crispy/QCPlot.py
crispy/Utils.py
crispy/__init__.py
crispy/data/GrowthRates_v1.3.0_20190222.csv
crispy/data/SIDMvsMedia.xlsx
crispy/data/cytoBand.txt
crispy/data/example_copynumber.csv
crispy/data/example_rawcounts.csv
crispy/data/growth_rates_rapid_screen_1536_v1.6.3_02Jun20.csv
crispy/data/model_list_20200204.csv
crispy/data/copy_number/Summary_segmentation_data_994_lines_picnic.csv.gz
crispy/data/crispr/CRISPR_Institute_Origin_20191108.csv.gz
crispy/data/crispr_libs/Avana_v1.csv.gz
crispy/data/crispr_libs/Brunello_v1.csv.gz
crispy/data/crispr_libs/GeCKO_v2.csv.gz
crispy/data/crispr_libs/Manjunath_Wu_v1.csv.gz
crispy/data/crispr_libs/MasterLib_v1.csv.gz
crispy/data/crispr_libs/MinLibCas9.csv.gz
crispy/data/crispr_libs/Sabatini_Lander_v3.csv.gz
crispy/data/crispr_libs/TKOv3.csv.gz
crispy/data/crispr_libs/Yusa_v1.1.csv.gz
crispy/data/crispr_manifests/Avana_DepMap19Q2_dropped_guides.csv.gz
crispy/data/crispr_manifests/Avana_DepMap19Q2_sample_map.csv.gz
crispy/data/crispr_manifests/Avana_DepMap19Q3_dropped_guides.csv
crispy/data/crispr_manifests/Avana_DepMap19Q3_sample_map.csv.gz
crispy/data/crispr_manifests/Avana_DepMap20Q1_dropped_guides.csv
crispy/data/crispr_manifests/Avana_DepMap20Q1_sample_map.csv.gz
crispy/data/crispr_manifests/Avana_DepMap20Q2_dropped_guides.csv
crispy/data/crispr_manifests/Avana_DepMap20Q2_high_variance_genes.csv
crispy/data/crispr_manifests/Avana_DepMap20Q2_sample_map.csv.gz
crispy/data/crispr_manifests/GeCKO2_Achilles_v3.3.8_dropped_guides.csv.gz
crispy/data/crispr_manifests/KM12_coverage_samplesheet.xlsx
crispy/data/crispr_manifests/project_score_all_qc_failed_samples.csv
crispy/data/crispr_manifests/project_score_exclude_samples.csv
cy-0.5.8.dist-info/LICENSE
cy-0.5.8.dist-info/METADATA
cy-0.5.8.dist-info/WHEEL
cy-0.5.8.dist-info/top_level.txt
cy-0.5.8.dist-info/RECORD
