Metadata-Version: 2.1
Name: cy
Version: 0.5.8
Summary: Modelling CRISPR dropout data
Home-page: https://github.com/EmanuelGoncalves/crispy
Author: Emanuel Goncalves
Author-email: eg14@sanger.ac.uk
License: UNKNOWN
Platform: UNKNOWN
Classifier: Programming Language :: Python :: 3
Classifier: License :: OSI Approved :: BSD License
Classifier: Operating System :: OS Independent
Classifier: Intended Audience :: Science/Research
Classifier: Topic :: Scientific/Engineering :: Bio-Informatics
Classifier: Topic :: Scientific/Engineering :: Information Analysis
Requires-Dist: numpy (>=1.13)
Requires-Dist: scipy (>=0.19)
Requires-Dist: pandas (>=0.20)
Requires-Dist: xlrd (>=1.0.0)
Requires-Dist: openpyxl
Requires-Dist: scikit-learn (>=0.18)
Requires-Dist: matplotlib (>=2.0)
Requires-Dist: seaborn (>=0.7)
Requires-Dist: natsort (>=5.1.0)
Requires-Dist: statsmodels (>=0.8.0)
Requires-Dist: pybedtools (>=0.7.10)
Requires-Dist: adjustText
